slots/__init__.py
slots/slot_repository.py
slots/slots.py
slots/test/__init__.py
slots/test/conftest.py
slots/test/test_slot_repository.py
slots/test/test_slots.py
slotserver/__init__.py
slotserver/slot_flask_server.py
slotserver/slot_http_client.py
slotserver/slot_repository.py
slotserver/slot_service.py
slotserver/slots.py
slotserver/test/__init__.py
slotserver/test/conftest.py
slotserver/test/test_slot_flask_server.py
slotserver/test/test_slot_http_client.py
slotserver/test/test_slot_repository.py
slotserver/test/test_slot_service.py
slotserver/test/test_slots.py
slotserver-0.0.4.dist-info/LICENSE
slotserver-0.0.4.dist-info/METADATA
slotserver-0.0.4.dist-info/WHEEL
slotserver-0.0.4.dist-info/top_level.txt
slotserver-0.0.4.dist-info/RECORD
