Metadata-Version: 2.1
Name: slotserver
Version: 0.0.4
Summary: IOT Dashboard data relay
Home-page: https://github.com/h-dub/slotserver
Author: Hugh Wade
Author-email: hugh@hdub.io
License: UNKNOWN
Platform: UNKNOWN
Classifier: Programming Language :: Python :: 3
Classifier: License :: OSI Approved :: MIT License
Classifier: Operating System :: OS Independent
Requires-Python: >=3.8
